packtrack/__init__.py
packtrack/correios.py
packtrack/dhl_gm.py
packtrack/royal.py
packtrack/scraping.py
packtrack-1.6.dist-info/COPYING
packtrack-1.6.dist-info/METADATA
packtrack-1.6.dist-info/WHEEL
packtrack-1.6.dist-info/top_level.txt
packtrack-1.6.dist-info/RECORD
