Metadata-Version: 2.1
Name: packtrack
Version: 1.6
Summary: API Python para obter informacoes de encomendas
Home-page: https://github.com/aleborba/packtrack
Author: Ale Borba
Author-email: ale.borba@codingforchange.com
License: LGPLv3
Keywords: encomendas track api
Platform: UNKNOWN
Requires-Dist: BeautifulSoup (>=3.1.0)
Requires-Dist: requests (>=0.14.2)
Requires-Dist: beautifulsoup4 (>=4.3.2)
Requires-Dist: lxml (>=2.3.5)
Requires-Dist: zeep (>=1.6.0)
